ros2_msg_transform/__init__.py
ros2_msg_transform/ros2_conv.py
ros2_msg_transform-0.2.2.dist-info/LICENSE
ros2_msg_transform-0.2.2.dist-info/METADATA
ros2_msg_transform-0.2.2.dist-info/WHEEL
ros2_msg_transform-0.2.2.dist-info/RECORD
